fast_negative_binomial/__init__.py
fast_negative_binomial/fast_negative_binomial.cpython-310-darwin.so
fast_negative_binomial/.dylibs/libomp.dylib
fast_negative_binomial-1.0.1.data/data/bin/fast_nb
fast_negative_binomial-1.0.1.data/data/include/fast_negative_binomial/fast_nb.hpp
fast_negative_binomial-1.0.1.data/data/include/fast_negative_binomial/log_comb_gcc.hpp
fast_negative_binomial-1.0.1.data/data/include/fast_negative_binomial/log_comb.hpp
fast_negative_binomial-1.0.1.data/data/include/fast_negative_binomial/cache.hpp
fast_negative_binomial-1.0.1.data/data/include/fast_negative_binomial/eigen_nb.hpp
fast_negative_binomial-1.0.1.data/data/include/fast_negative_binomial/base_nb.hpp
fast_negative_binomial-1.0.1.data/data/include/fast_negative_binomial/optimise.hpp
fast_negative_binomial-1.0.1.data/data/include/fast_negative_binomial/vector_nb.hpp
fast_negative_binomial-1.0.1.data/data/include/fast_negative_binomial/eigen_nb_cdf.hpp
fast_negative_binomial-1.0.1.data/data/include/fast_negative_binomial/eigen_nb_jac.hpp
fast_negative_binomial-1.0.1.data/data/include/fast_negative_binomial/eigen_nb_icdf.hpp
fast_negative_binomial-1.0.1.data/data/include/fast_negative_binomial/utils.hpp
fast_negative_binomial-1.0.1.data/data/lib/libfast_nb_lib.a
fast_negative_binomial-1.0.1.data/data/lib/python_modules/fast_negative_binomial.cpython-310-darwin.so
fast_negative_binomial-1.0.1.data/data/lib/cmake/FastNB/FastNBConfig.cmake
fast_negative_binomial-1.0.1.data/data/lib/cmake/FastNB/FastNBTargets.cmake
fast_negative_binomial-1.0.1.data/data/lib/cmake/FastNB/FastNBTargets-release.cmake
fast_negative_binomial-1.0.1.data/data/lib/cmake/FastNB/FastNBConfigVersion.cmake
fast_negative_binomial-1.0.1.dist-info/RECORD
fast_negative_binomial-1.0.1.dist-info/WHEEL
fast_negative_binomial-1.0.1.dist-info/top_level.txt
fast_negative_binomial-1.0.1.dist-info/METADATA
fast_negative_binomial-1.0.1.dist-info/licenses/LICENSE
