Metadata-Version: 2.4
Name: fast_negative_binomial
Version: 1.0.1
Summary: Python bindings for Negative Binomial PMF
Author: Daniel O'Hanlon
Author-email: dpohanlon@gmail.com
License: MIT
Classifier: Programming Language :: Python :: 3
Classifier: Programming Language :: C++
Classifier: Operating System :: OS Independent
Classifier: License :: OSI Approved :: MIT License
Classifier: Operating System :: POSIX
Classifier: Operating System :: Microsoft :: Windows
Classifier: Operating System :: MacOS
Requires-Python: >=3.9,<4.0
License-File: LICENSE
Requires-Dist: numpy>=1.18.0
Requires-Dist: pybind11>=2.6
Dynamic: author
Dynamic: author-email
Dynamic: classifier
Dynamic: license
Dynamic: license-file
Dynamic: requires-dist
Dynamic: requires-python
Dynamic: summary
